dropshare/__init__.py
dropshare/back.py
dropshare/front.py
dropshare/git.py
dropshare/repo.py
dropshare/store.py
dropshare/tools.py
git_dropshare-0.1.4.dist-info/DESCRIPTION.rst
git_dropshare-0.1.4.dist-info/METADATA
git_dropshare-0.1.4.dist-info/RECORD
git_dropshare-0.1.4.dist-info/WHEEL
git_dropshare-0.1.4.dist-info/entry_points.txt
git_dropshare-0.1.4.dist-info/metadata.json
git_dropshare-0.1.4.dist-info/top_level.txt
