Metadata-Version: 2.0
Name: git-dropshare
Version: 0.1.4
Summary: Git plus Dropbox sharing for binary documents.
Home-page: https://github.com/paudebau/git-dropshare
Author: Philippe Audebaud <paudebau@gmail.com>
Author-email: paudebau@gmail.com
License: Gnu Public License v3
Platform: UNKNOWN
Classifier: Development Status :: 4 - Beta
Classifier: Environment :: Console
Classifier: Intended Audience :: Developers
Classifier: License :: OSI Approved :: GNU General Public License v3 or later (GPLv3+)
Classifier: Natural Language :: English
Classifier: Operating System :: Unix
Classifier: Operating System :: MacOS :: MacOS X
Classifier: Programming Language :: Python :: 3.6
Classifier: Topic :: Software Development :: Libraries
Classifier: Topic :: Software Development :: Version Control
Classifier: Topic :: Utilities
Requires-Dist: dropbox (>=8)
Requires-Dist: gitpython (>=2)
